{"name":"Inicio de sesión sin colocar usuario","id":"iniciar-sesión-en-saucedemo;inicio-de-sesión-sin-colocar-usuario","scenarioId":"login:Inicio de sesión sin colocar usuario","methodName":"Inicio de sesión sin colocar usuario","testSteps":[{"number":1,"description":"Dado que el usuario abre la página de SauceDemo","duration":1594,"startTime":"2026-02-27T06:45:53.824030200-05:00[America/Lima]","screenshots":[{"screenshot":"4e330fd8cd0d1afae04071fb92d313443563b8fb92e5cb2196b031ce17252c92.png","timeStamp":1772192755418,"screenshotName":"4e330fd8cd0d1afae04071fb92d313443563b8fb92e5cb2196b031ce17252c92.png"}],"result":"SUCCESS","precondition":false,"level":0,"children":[{"number":2,"description":"Abrir la pagina de SauceDemo","duration":1572,"startTime":"2026-02-27T06:45:53.844034600-05:00[America/Lima]","screenshots":[{"screenshot":"4e330fd8cd0d1afae04071fb92d313443563b8fb92e5cb2196b031ce17252c92.png","timeStamp":1772192755416,"screenshotName":"4e330fd8cd0d1afae04071fb92d313443563b8fb92e5cb2196b031ce17252c92.png"}],"result":"SUCCESS","precondition":false,"level":1}]},{"number":3,"description":"Cuando escribo el usuario \"\"","duration":165,"startTime":"2026-02-27T06:45:55.419075400-05:00[America/Lima]","screenshots":[{"screenshot":"4e5b5d8d93eaee4a4b9a7271ea1e265048cc60e6adfa28462469bb201546d5b6.png","timeStamp":1772192755584,"screenshotName":"4e5b5d8d93eaee4a4b9a7271ea1e265048cc60e6adfa28462469bb201546d5b6.png"}],"result":"SUCCESS","precondition":false,"level":0,"children":[{"number":4,"description":"Escribir el usuario","duration":161,"startTime":"2026-02-27T06:45:55.420075300-05:00[America/Lima]","screenshots":[{"screenshot":"4e5b5d8d93eaee4a4b9a7271ea1e265048cc60e6adfa28462469bb201546d5b6.png","timeStamp":1772192755581,"screenshotName":"4e5b5d8d93eaee4a4b9a7271ea1e265048cc60e6adfa28462469bb201546d5b6.png"}],"result":"SUCCESS","precondition":false,"level":1}]},{"number":5,"description":"Y escribo la contraseña \"secret_sauce\"","duration":165,"startTime":"2026-02-27T06:45:55.584270600-05:00[America/Lima]","screenshots":[{"screenshot":"e33bcf25caac7c75da22cbdbaeaea1f2df5e254ee9a15b37a8e4168ab2f4a285.png","timeStamp":1772192755749,"screenshotName":"e33bcf25caac7c75da22cbdbaeaea1f2df5e254ee9a15b37a8e4168ab2f4a285.png"}],"result":"SUCCESS","precondition":false,"level":0,"children":[{"number":6,"description":"Escribir la contraseña","duration":160,"startTime":"2026-02-27T06:45:55.586269900-05:00[America/Lima]","screenshots":[{"screenshot":"e33bcf25caac7c75da22cbdbaeaea1f2df5e254ee9a15b37a8e4168ab2f4a285.png","timeStamp":1772192755746,"screenshotName":"e33bcf25caac7c75da22cbdbaeaea1f2df5e254ee9a15b37a8e4168ab2f4a285.png"}],"result":"SUCCESS","precondition":false,"level":1}]},{"number":7,"description":"Y hago click en el boton Login","duration":214,"startTime":"2026-02-27T06:45:55.750800700-05:00[America/Lima]","screenshots":[{"screenshot":"2c9824a987a374163828fc5ea9a40bf648f95969275b8dbc62350254a7c84d09.png","timeStamp":1772192755965,"screenshotName":"2c9824a987a374163828fc5ea9a40bf648f95969275b8dbc62350254a7c84d09.png"}],"result":"SUCCESS","precondition":false,"level":0,"children":[{"number":8,"description":"Presionar Login","duration":210,"startTime":"2026-02-27T06:45:55.751800400-05:00[America/Lima]","screenshots":[{"screenshot":"2c9824a987a374163828fc5ea9a40bf648f95969275b8dbc62350254a7c84d09.png","timeStamp":1772192755962,"screenshotName":"2c9824a987a374163828fc5ea9a40bf648f95969275b8dbc62350254a7c84d09.png"}],"result":"SUCCESS","precondition":false,"level":1}]},{"number":9,"description":"Entonces se debe mostrar el mensaje de error \"Epic sadface: Username is required\"","duration":37,"startTime":"2026-02-27T06:45:55.965352200-05:00[America/Lima]","screenshots":[{"screenshot":"2c9824a987a374163828fc5ea9a40bf648f95969275b8dbc62350254a7c84d09.png","timeStamp":1772192756002,"screenshotName":"2c9824a987a374163828fc5ea9a40bf648f95969275b8dbc62350254a7c84d09.png"}],"result":"SUCCESS","precondition":false,"level":0,"children":[{"number":10,"description":"Validar mensaje de error en login","duration":33,"startTime":"2026-02-27T06:45:55.966353100-05:00[America/Lima]","screenshots":[{"screenshot":"2c9824a987a374163828fc5ea9a40bf648f95969275b8dbc62350254a7c84d09.png","timeStamp":1772192755999,"screenshotName":"2c9824a987a374163828fc5ea9a40bf648f95969275b8dbc62350254a7c84d09.png"}],"result":"SUCCESS","precondition":false,"level":1}]}],"userStory":{"id":"login","storyName":"Iniciar sesión en SauceDemo","displayName":"Iniciar sesión en SauceDemo","path":"login","pathElements":[{"name":"login","description":""}],"type":"feature"},"title":"Inicio de sesión sin colocar usuario","description":"","backgroundTitle":"","backgroundDescription":"","tags":[{"name":"unhappypath","type":"tag","displayName":"unhappypath"},{"name":"Chrome","type":"context","displayName":"Chrome"},{"name":"Windows","type":"context","displayName":"Windows"},{"name":"login","type":"tag","displayName":"login"},{"name":"SAUCE4","type":"tag","displayName":"SAUCE4"},{"name":"Chrome, Windows","type":"context","displayName":"Chrome, Windows"}],"startTime":"2026-02-27T06:45:53.822028600-05:00[America/Lima]","duration":1517,"projectKey":"","sessionId":"4583b505771b137ea86ed6f919496ce3","driver":"chrome","isManualTestingUpToDate":false,"context":"chrome,windows","manual":false,"testSource":"Cucumber","order":0,"result":"SUCCESS"}